b64s/__init__.py
b64s/py.typed
b64s-0.1.0.dist-info/COPYING
b64s-0.1.0.dist-info/METADATA
b64s-0.1.0.dist-info/WHEEL
b64s-0.1.0.dist-info/RECORD
