Metadata-Version: 2.1
Name: b64s
Version: 0.1.0
Summary: Base64 with UTF-8 str input and output
Home-page: https://github.com/EliahKagan/b64s
License: CC0-1.0
Keywords: base64,decoding,encoding,text,utf-8
Author: Eliah Kagan
Author-email: degeneracypressure@gmail.com
Requires-Python: >=3.7,<4.0
Classifier: Development Status :: 3 - Alpha
Classifier: Intended Audience :: Developers
Classifier: License :: CC0 1.0 Universal (CC0 1.0) Public Domain Dedication
Classifier: Programming Language :: Python :: 3
Classifier: Programming Language :: Python :: 3.7
Classifier: Programming Language :: Python :: 3.8
Classifier: Programming Language :: Python :: 3.9
Classifier: Programming Language :: Python :: 3.10
Classifier: Programming Language :: Python :: 3.11
Project-URL: Repository, https://github.com/EliahKagan/b64s
